stack/__init__.py
stack/request.py
stack/response.py
stack/servers.py
stackhttp/__init__.py
stackhttp/request.py
stackhttp/response.py
stackhttp/servers.py
stackhttp-1.1.1.dist-info/LICENSE
stackhttp-1.1.1.dist-info/METADATA
stackhttp-1.1.1.dist-info/WHEEL
stackhttp-1.1.1.dist-info/top_level.txt
stackhttp-1.1.1.dist-info/RECORD
